twitter_profile_predictor/__init__.py
twitter_profile_predictor/bios_analyzer.py
twitter_profile_predictor/data/Keywords_professions_statuses.xlsx
twitter_profile_predictor/data/df_words_classes_3.xlsx
twitter_profile_predictor/data/df_words_twitterUsersAnalysis.xlsx
twitter_profile_predictor-0.2.2.dist-info/METADATA
twitter_profile_predictor-0.2.2.dist-info/WHEEL
twitter_profile_predictor-0.2.2.dist-info/top_level.txt
twitter_profile_predictor-0.2.2.dist-info/RECORD
